herokutils/__init__.py
herokutils/utils.py
herokutils-0.0.1.dist-info/LICENSE.txt
herokutils-0.0.1.dist-info/METADATA
herokutils-0.0.1.dist-info/WHEEL
herokutils-0.0.1.dist-info/top_level.txt
herokutils-0.0.1.dist-info/RECORD
