Metadata-Version: 2.1
Name: herokutils
Version: 0.0.1
Summary: utilities for heroku deployment
Home-page: UNKNOWN
Author: Sebastien Villard
Author-email: sebastien.villard@gmail.com
License: MIT
Platform: UNKNOWN
Requires-Dist: pandas (>=1.1.0)
Requires-Dist: nltk (>=3)
Requires-Dist: numpy (>=1.19)
Requires-Dist: scikit-learn (>=0.23)
